icij_common/__init__.py
icij_common/fastapi_utils.py
icij_common/import_utils.py
icij_common/logging_utils.py
icij_common/pydantic_utils.py
icij_common/registrable.py
icij_common/test_utils.py
icij_common/es/__init__.py
icij_common/neo4j_/__init__.py
icij_common/neo4j_/constants.py
icij_common/neo4j_/db.py
icij_common/neo4j_/migrate.py
icij_common/neo4j_/test_utils.py
icij_common-0.7.3.dist-info/METADATA
icij_common-0.7.3.dist-info/WHEEL
icij_common-0.7.3.dist-info/RECORD
